pre_commit_ci_config.py
pre_commit_ci_config-1.6.1.dist-info/LICENSE
pre_commit_ci_config-1.6.1.dist-info/METADATA
pre_commit_ci_config-1.6.1.dist-info/WHEEL
pre_commit_ci_config-1.6.1.dist-info/entry_points.txt
pre_commit_ci_config-1.6.1.dist-info/top_level.txt
pre_commit_ci_config-1.6.1.dist-info/RECORD
