Metadata-Version: 2.1
Name: pre-commit-ci-config
Version: 1.6.1
Summary: validation for pre-commit.ci configuration
Home-page: https://github.com/pre-commit-ci/pre-commit-ci-config
Author: Anthony Sottile
Author-email: asottile@umich.edu
License: MIT
Classifier: License :: OSI Approved :: MIT License
Classifier: Programming Language :: Python :: 3
Classifier: Programming Language :: Python :: 3 :: Only
Classifier: Programming Language :: Python :: Implementation :: CPython
Classifier: Programming Language :: Python :: Implementation :: PyPy
Requires-Python: >=3.8
License-File: LICENSE
Requires-Dist: cfgv (>=2.0.0)
Requires-Dist: pyyaml (>=5.1)
